satcfdi/__init__.py
satcfdi/__version__.py
satcfdi/ans1e.py
satcfdi/cfdi.py
satcfdi/exceptions.py
satcfdi/help.py
satcfdi/sat_requests_utils.py
satcfdi/utils.py
satcfdi/xelement.py
satcfdi/zip.py
satcfdi/accounting/__init__.py
satcfdi/accounting/_ansi_colors.py
satcfdi/accounting/contabilidad.py
satcfdi/accounting/contabilidad_print.py
satcfdi/accounting/formatters.py
satcfdi/accounting/models.py
satcfdi/accounting/process.py
satcfdi/apis/__init__.py
satcfdi/apis/banxico.py
satcfdi/catalogs/__init__.py
satcfdi/catalogs/catalogs.db
satcfdi/certifica/__init__.py
satcfdi/certifica/pkcs7.py
satcfdi/cli/__init__.py
satcfdi/cli/main.py
satcfdi/create/__init__.py
satcfdi/create/catalogos.py
satcfdi/create/compute.py
satcfdi/create/addendas/__init__.py
satcfdi/create/addendas/dvz11.py
satcfdi/create/cancela/__init__.py
satcfdi/create/cancela/aceptacionrechazo.py
satcfdi/create/cancela/cancelacion.py
satcfdi/create/cancela/cancelacionretencion.py
satcfdi/create/cfd/__init__.py
satcfdi/create/cfd/aerolineas10.py
satcfdi/create/cfd/aieps10.py
satcfdi/create/cfd/cartaporte10.py
satcfdi/create/cfd/cartaporte20.py
satcfdi/create/cfd/cartaporte30.py
satcfdi/create/cfd/cartaporte31.py
satcfdi/create/cfd/catalogos.py
satcfdi/create/cfd/cce10.py
satcfdi/create/cfd/cce11.py
satcfdi/create/cfd/cce20.py
satcfdi/create/cfd/cfdi32.py
satcfdi/create/cfd/cfdi33.py
satcfdi/create/cfd/cfdi40.py
satcfdi/create/cfd/consumodecombustibles10.py
satcfdi/create/cfd/consumodecombustibles11.py
satcfdi/create/cfd/decreto10.py
satcfdi/create/cfd/destruccion10.py
satcfdi/create/cfd/detallista.py
satcfdi/create/cfd/divisas10.py
satcfdi/create/cfd/donat11.py
satcfdi/create/cfd/ecb10.py
satcfdi/create/cfd/ecc.py
satcfdi/create/cfd/ecc11.py
satcfdi/create/cfd/ecc12.py
satcfdi/create/cfd/gceh10.py
satcfdi/create/cfd/iedu10.py
satcfdi/create/cfd/ieeh10.py
satcfdi/create/cfd/implocal10.py
satcfdi/create/cfd/ine10.py
satcfdi/create/cfd/ine11.py
satcfdi/create/cfd/leyendasFisc10.py
satcfdi/create/cfd/nomina11.py
satcfdi-4.9.3.dist-info/METADATA
satcfdi-4.9.3.dist-info/WHEEL
satcfdi-4.9.3.dist-info/entry_points.txt
satcfdi-4.9.3.dist-info/top_level.txt
satcfdi-4.9.3.dist-info/RECORD
