Metadata-Version: 2.4
Name: satcfdi
Version: 4.9.3
Summary: The best open-source python library to generate and process SAT's CFDI
Home-page: https://github.com/SAT-CFDI/python-satcfdi
Author: satcfdi@outlook.com
Author-email: satcfdi@outlook.com
License: MIT License
Project-URL: Documentation, https://satcfdi.readthedocs.io
Project-URL: Source, https://github.com/SAT-CFDI/python-satcfdi
Keywords: cfdi,sat,facturación,comprobante,retenciones,nómina,pagos,carta porte,contabilidad,e-invoicing,DIOT
Classifier: Development Status :: 5 - Production/Stable
Classifier: Intended Audience :: Developers
Classifier: License :: OSI Approved :: MIT License
Classifier: Natural Language :: Spanish
Classifier: Operating System :: OS Independent
Classifier: Programming Language :: Python :: 3.11
Classifier: Programming Language :: Python :: 3.12
Classifier: Programming Language :: Python :: 3.13
Classifier: Programming Language :: Python :: 3.14
Requires-Python: >=3.11
Requires-Dist: jinja2>=3.0.0
Requires-Dist: lxml>=4.9.0
Requires-Dist: weasyprint>=57.0
Requires-Dist: requests>=2.0.0
Requires-Dist: cryptography>=43.0.1
Requires-Dist: pytz>=2022.5
Requires-Dist: xlsxwriter>=3.0.0
Requires-Dist: pyOpenSSL>=22.0.0
Requires-Dist: qrcode>=7.3.0
Requires-Dist: tabulate>=0.9.0
Requires-Dist: packaging>=21.0
Requires-Dist: beautifulsoup4>4.11.0
Provides-Extra: test
Requires-Dist: coverage; extra == "test"
Requires-Dist: pytest; extra == "test"
Requires-Dist: PyYAML; extra == "test"
Provides-Extra: docs
Requires-Dist: Sphinx>=5.3.0; extra == "docs"
Requires-Dist: sphinx-rtd-theme>=1.1.1; extra == "docs"
Dynamic: author
Dynamic: author-email
Dynamic: classifier
Dynamic: description
Dynamic: description-content-type
Dynamic: home-page
Dynamic: keywords
Dynamic: license
Dynamic: project-url
Dynamic: provides-extra
Dynamic: requires-dist
Dynamic: requires-python
Dynamic: summary
